{"results": {"total_iterations": 7, "title": "bng_flow_stats", "Elapsed Time": 280.72222924232483, "queue_full_percentage": 0.0, "drop_rate_percentage": 0, "valid_latency": true, "rate_tx_bps": 18141536256.0, "rate_rx_bps": 18130688000.0, "tx_util": 19.537038976, "latency": {}, "cpu_util": 6.0597243309021, "tx_pps": 8721892.0, "bw_per_core": 24.9482421875, "rx_pps": 8716678.0, "rate_p": 19.53125, "total_tx_L1": 19537038976.0, "total_rx_L1": 19525356480.0, "tx_bps": 18141536256.0, "rx_bps": 18130688000.0, "max_rate_bps": 92871057408.0, "iteration": 6, "rate_difference": 0, "ndr_points": [18141536256.0]}, "config": {"iteration_duration": 40.0, "q_full_resolution": 2.0, "first_run_duration": 40.0, "pdr": 0.1, "pdr_error": 1.0, "ndr_results": 1, "max_iterations": 10, "ports": [0, 1], "cores": 24, "total_cores": 24, "verbose": false, "bi_dir": false, "plugin_file": null, "tunables": {}, "opt_binary_search": false, "title": "bng_flow_stats", "opt_binary_search_percentage": 5}}