{"results": {"total_iterations": 0, "title": "bng_flow_stats", "Elapsed Time": 35.14548921585083, "queue_full_percentage": 0.0, "drop_rate_percentage": 0, "valid_latency": true, "rate_tx_bps": 14006259712.0, "rate_rx_bps": 13938373632.0, "tx_util": 18.383216512, "latency": {}, "cpu_util": 97.9327392578125, "tx_pps": 27355980.0, "bw_per_core": 3.575479507446289, "rx_pps": 27223384.0, "rate_p": 100.0, "total_tx_L1": 18383216512.0, "total_rx_L1": 18294115072.0, "tx_bps": 14006259712.0, "rx_bps": 13938373632.0, "max_rate_bps": 14006259712.0, "ndr_points": [14006259712.0]}, "config": {"iteration_duration": 40.0, "q_full_resolution": 2.0, "first_run_duration": 40.0, "pdr": 0.1, "pdr_error": 1.0, "ndr_results": 1, "max_iterations": 10, "ports": [0, 1], "cores": 8, "total_cores": 8, "verbose": false, "bi_dir": false, "plugin_file": null, "tunables": {}, "opt_binary_search": false, "title": "bng_flow_stats", "opt_binary_search_percentage": 5}}