{"results": {"total_iterations": 0, "title": "bng_flow_stats", "Elapsed Time": 35.09646463394165, "queue_full_percentage": 0.0, "drop_rate_percentage": 0, "valid_latency": true, "rate_tx_bps": 40051437568.0, "rate_rx_bps": 40055119872.0, "tx_util": 52.567515648, "latency": {}, "cpu_util": 98.3609848022461, "tx_pps": 78225488.0, "bw_per_core": 4.071882247924805, "rx_pps": 78232664.0, "rate_p": 100.0, "total_tx_L1": 52567515648.0, "total_rx_L1": 52572346112.0, "tx_bps": 40051437568.0, "rx_bps": 40055119872.0, "max_rate_bps": 40051437568.0, "ndr_points": [40051437568.0]}, "config": {"iteration_duration": 40.0, "q_full_resolution": 2.0, "first_run_duration": 40.0, "pdr": 0.1, "pdr_error": 1.0, "ndr_results": 1, "max_iterations": 10, "ports": [0, 1], "cores": 20, "total_cores": 20, "verbose": false, "bi_dir": false, "plugin_file": null, "tunables": {}, "opt_binary_search": false, "title": "bng_flow_stats", "opt_binary_search_percentage": 5}}